odoo/addons/website_no_crawler/README.rst
odoo/addons/website_no_crawler/__init__.py
odoo/addons/website_no_crawler/__manifest__.py
odoo/addons/website_no_crawler/i18n/website_no_crawler.pot
odoo/addons/website_no_crawler/readme/CONTRIBUTORS.rst
odoo/addons/website_no_crawler/readme/DESCRIPTION.rst
odoo/addons/website_no_crawler/readme/USAGE.rst
odoo/addons/website_no_crawler/static/description/icon.png
odoo/addons/website_no_crawler/static/description/index.html
odoo/addons/website_no_crawler/views/disable_robots.xml
odoo11_addon_website_no_crawler-11.0.1.1.0.dist-info/METADATA
odoo11_addon_website_no_crawler-11.0.1.1.0.dist-info/WHEEL
odoo11_addon_website_no_crawler-11.0.1.1.0.dist-info/top_level.txt
odoo11_addon_website_no_crawler-11.0.1.1.0.dist-info/RECORD
